distributedlock/__init__.py
DistributedLockCron-3.0.0.dist-info/LICENSE
DistributedLockCron-3.0.0.dist-info/METADATA
DistributedLockCron-3.0.0.dist-info/WHEEL
DistributedLockCron-3.0.0.dist-info/top_level.txt
DistributedLockCron-3.0.0.dist-info/RECORD
